clearscreen/__init__.py
clearscreen/art/__init__.py
clearscreen/art/alien.txt
clearscreen/art/bippy.txt
clearscreen/art/bird.txt
clearscreen/art/borbox.txt
clearscreen/art/callingproxy.txt
clearscreen/art/chilltime.txt
clearscreen/art/clawgrip.txt
clearscreen/art/clock.txt
clearscreen/art/cloudpancakes.txt
clearscreen/art/coach.txt
clearscreen/art/duck.txt
clearscreen/art/equine.txt
clearscreen/art/face.txt
clearscreen/art/failuretolaunch.txt
clearscreen/art/fish.txt
clearscreen/art/flask.txt
clearscreen/art/frog.txt
clearscreen/art/frogcopter.txt
clearscreen/art/hamburger.txt
clearscreen/art/irabug.txt
clearscreen/art/italicface.txt
clearscreen/art/king.txt
clearscreen/art/krang.txt
clearscreen/art/macaroni.txt
clearscreen/art/map.txt
clearscreen/art/marsguy.txt
clearscreen/art/mgear1.txt
clearscreen/art/mgear2.txt
clearscreen/art/mgear3.txt
clearscreen/art/mk2killer.txt
clearscreen/art/mouse.txt
clearscreen/art/nerd.txt
clearscreen/art/professor.txt
clearscreen/art/reffy.txt
clearscreen/art/riley.txt
clearscreen/art/rocket.txt
clearscreen/art/ruffy.txt
clearscreen/art/samurai.txt
clearscreen/art/sea.txt
clearscreen/art/smileyface2.txt
clearscreen/art/smileyface3.txt
clearscreen/art/sneakypete.txt
clearscreen/art/standandcrouch.txt
clearscreen/art/themountains.txt
clearscreen/art/train.txt
clearscreen/art/turtle.txt
clearscreen/art/weinerdog.txt
clearscreen/art/wippypo.txt
clearscreen/art/x.txt
clearscreen/art/yay.txt
clearscreen/cli.py
clearscreen-0.2.1.dist-info/entry_points.txt
clearscreen-0.2.1.dist-info/WHEEL
clearscreen-0.2.1.dist-info/METADATA
clearscreen-0.2.1.dist-info/RECORD
