Metadata-Version: 2.1
Name: clearscreen
Version: 0.2.1
Summary: Draws random ascii art to the screen, making it easier to scroll back and find where you where.
Home-page: https://github.com/TimSimpson/cls
Author: Tim Simpson
Author-email: timsimpson4@gmail.com
Requires-Python: >=3.6,<4.0
Classifier: Programming Language :: Python :: 3
Classifier: Programming Language :: Python :: 3.6
Classifier: Programming Language :: Python :: 3.7
Classifier: Programming Language :: Python :: 3.8
Requires-Dist: colored (>=1.4.2,<2.0.0)
Project-URL: Repository, https://github.com/TimSimpson/cls
